mpact_benchmark/utils/tensor_generator.py
mpact_benchmark/utils/benchmark_utils.py
mpact_benchmark/benchmarks/lif_benchmark.py
mpact_benchmark/benchmarks/gcn_benchmark.py
mpact_benchmark/benchmarks/resnet_benchmark.py
mpact_benchmark/benchmarks/kernels_benchmark.py
mpact/mpactbackend.py
mpact/passmanager.py
mpact/execution_engine.py
mpact/ir.py
mpact/dialects/cf.py
mpact/dialects/_amdgpu_ops_gen.py
mpact/dialects/_affine_enum_gen.py
mpact/dialects/_transform_ops_gen.py
mpact/dialects/_tensor_ops_gen.py
mpact/dialects/_nvvm_enum_gen.py
mpact/dialects/_nvgpu_ops_gen.py
mpact/dialects/_spirv_ops_gen.py
mpact/dialects/arith.py
mpact/dialects/builtin.py
mpact/dialects/sparse_tensor.py
mpact/dialects/openmp.py
mpact/dialects/_vector_enum_gen.py
mpact/dialects/_memref_transform_ops_gen.py
mpact/dialects/_vector_ops_gen.py
mpact/dialects/rocdl.py
mpact/dialects/_async_ops_gen.py
mpact/dialects/_memref_ops_gen.py
mpact/dialects/_omp_ops_gen.py
mpact/dialects/_tensor_transform_ops_gen.py
mpact/dialects/_nvgpu_enum_gen.py
mpact/dialects/_llvm_enum_gen.py
mpact/dialects/llvm.py
mpact/dialects/_gpu_enum_gen.py
mpact/dialects/complex.py
mpact/dialects/scf.py
mpact/dialects/_math_ops_gen.py
mpact/dialects/_complex_ops_gen.py
mpact/dialects/quant.py
mpact/dialects/_transform_enum_gen.py
mpact/dialects/pdl.py
mpact/dialects/_torch_ops_gen.py
mpact/dialects/_rocdl_ops_gen.py
mpact/dialects/_vector_transform_ops_gen.py
mpact/dialects/_gpu_transform_ops_gen.py
mpact/dialects/affine.py
mpact/dialects/_sparse_tensor_ops_gen.py
mpact/dialects/_ml_program_ops_gen.py
mpact/dialects/_func_ops_gen.py
mpact/dialects/_cf_ops_gen.py
mpact/dialects/vector.py
mpact/dialects/_sparse_tensor_transform_ops_gen.py
mpact/dialects/ml_program.py
mpact/dialects/_bufferization_enum_gen.py
mpact/dialects/_builtin_ops_gen.py
mpact/dialects/_structured_transform_enum_gen.py
mpact/dialects/_index_enum_gen.py
mpact/dialects/_llvm_ops_gen.py
mpact-20240607.dist-info/WHEEL
mpact-20240607.dist-info/top_level.txt
mpact-20240607.dist-info/RECORD
mpact-20240607.dist-info/LICENSE
mpact-20240607.dist-info/METADATA
