Metadata-Version: 2.1
Name: mpact
Version: 20240607
Summary: MPACT retargetable ML compiler
Author: Reid Tatge
Author-email: tatge@google.com
Requires-Python: >=3.8
License-File: LICENSE
Requires-Dist: numpy
Requires-Dist: packaging
